tulips/__init__.py
tulips/blackbody.py
tulips/ciexyz.py
tulips/colormodels.py
tulips/test_plots.py
tulips/tulips.py
astro_tulips-1.0.3.dist-info/LICENSE.rst
astro_tulips-1.0.3.dist-info/METADATA
astro_tulips-1.0.3.dist-info/WHEEL
astro_tulips-1.0.3.dist-info/top_level.txt
astro_tulips-1.0.3.dist-info/RECORD
