Metadata-Version: 2.1
Name: astro-tulips
Version: 1.0.3
Summary: Creates diagrams of stellar structures and their evolution
Home-page: https://bitbucket.org/elaplace/tulips/
Author: Eva Laplace
Author-email: eva.laplace67@gmail.com
License: GPLv3+
Classifier: Development Status :: 5 - Production/Stable
Classifier: Intended Audience :: Science/Research
Classifier: Programming Language :: Python :: 3
Classifier: License :: OSI Approved :: GNU General Public License v3 or later (GPLv3+)
Classifier: Topic :: Scientific/Engineering :: Astronomy
Classifier: Operating System :: OS Independent
Requires-Python: >=3.6
License-File: LICENSE.rst
Requires-Dist: numpy>=1.16
Requires-Dist: matplotlib>=3.3.2
Requires-Dist: mesaPlot>=1.1.0
Requires-Dist: tqdm
Requires-Dist: astropy>=4.0
Requires-Dist: imageio-ffmpeg>=0.2.0
Requires-Dist: ipywidgets
Requires-Dist: cmasher>=1.6.2
Provides-Extra: docs
Requires-Dist: sphinx; extra == "docs"
Provides-Extra: test
Requires-Dist: pytest; extra == "test"
